LICENSE
README.md
setup.py
fzf/__init__.py
fzf/fzf.py
fzf.py.egg-info/PKG-INFO
fzf.py.egg-info/SOURCES.txt
fzf.py.egg-info/dependency_links.txt
fzf.py.egg-info/top_level.txt