Metadata-Version: 2.1
Name: fzf.py
Version: 0.0.1
Summary: Python bindings for fzf
Home-page: http://packages.python.org/fzf
Author: Liam Scalzulli
Author-email: liam@scalzulli.com
License: CC0
Project-URL: Source Code, https://github.com/terror/fzf
Keywords: lib,bindings
Platform: UNKNOWN
Classifier: Development Status :: 3 - Alpha
Classifier: Topic :: Software Development :: Libraries
Classifier: License :: CC0 1.0 Universal (CC0 1.0) Public Domain Dedication
Requires-Python: >= 3.9
License-File: LICENSE
